accession2taxid.py
accession2taxid-1.0.5.dist-info/METADATA
accession2taxid-1.0.5.dist-info/WHEEL
accession2taxid-1.0.5.dist-info/entry_points.txt
accession2taxid-1.0.5.dist-info/top_level.txt
accession2taxid-1.0.5.dist-info/RECORD
