Metadata-Version: 2.1
Name: accession2taxid
Version: 1.0.5
Summary: Python library for NCBI assession2tax file querying.
Home-page: https://github.com/dafangs/accession2taxid
Author: dafangs
Author-email: dafangs@hotmail.com
License: MIT
Platform: UNKNOWN
Classifier: License :: OSI Approved :: MIT License
Classifier: Programming Language :: Python
Classifier: Programming Language :: Python :: 3
Classifier: Programming Language :: Python :: 3.6
Classifier: Programming Language :: Python :: Implementation :: CPython
Classifier: Programming Language :: Python :: Implementation :: PyPy
Requires-Python: >=3.6.0
Requires-Dist: click
Requires-Dist: redis
Requires-Dist: sqlalchemy
